pydalio/__init__.py
"pydalio/__main__,py"
pydalio/cli.py
pydalio/constants.py
pydalio/db.py
pydalio/principle.py
pydalio/utils.py
pydalio-0.1.0.dist-info/LICENSE
pydalio-0.1.0.dist-info/METADATA
pydalio-0.1.0.dist-info/WHEEL
pydalio-0.1.0.dist-info/entry_points.txt
pydalio-0.1.0.dist-info/RECORD
