Metadata-Version: 2.1
Name: pydalio
Version: 0.1.0
Summary: A package to help with testing of principles in decision making
Author: Tom Laumen
Author-email: tom_laumen@hotmail.com
Requires-Python: >=3.11,<4.0
Classifier: Programming Language :: Python :: 3
Classifier: Programming Language :: Python :: 3.11
Classifier: Programming Language :: Python :: 3.12
Requires-Dist: python-dotenv (>=1.0.1,<2.0.0)
Requires-Dist: pyyaml (>=6.0.2,<7.0.0)
Requires-Dist: typer (>=0.12.5,<0.13.0)
